{
    "m_IsActive": true,
    "m_Name": "Camera",
    "m_Transform": {
        "constrainPositionX": false,
        "constrainPositionY": false,
        "constrainPositionZ": false,
        "constrainRotationX": false,
        "constrainRotationY": false,
        "constrainRotationZ": false,
        "constrainScaleX": false,
        "constrainScaleY": false,
        "constrainScaleZ": false,
        "m_IsCamera": true,
        "m_Orientation": {
            "w": 0.9577688574790955,
            "x": 0.27916502952575684,
            "y": -0.0661369040608406,
            "z": 0.019277207553386688
        },
        "m_Position": {
            "x": 3.665572166442871,
            "y": 19.57292366027832,
            "z": 18.4245548248291
        },
        "m_Scale": {
            "x": 1.0,
            "y": 1.0,
            "z": 1.0
        }
    }
}